lattice_addons/lightning/__init__.py
lattice_addons/lightning/elastic.py
lattice_addons_lightning-0.1.1.dist-info/METADATA
lattice_addons_lightning-0.1.1.dist-info/WHEEL
lattice_addons_lightning-0.1.1.dist-info/top_level.txt
lattice_addons_lightning-0.1.1.dist-info/RECORD
